README.rst
setup.py
globalbedo_prior/GlobAlbedoPrior.py
globalbedo_prior/__init__.py
globalbedo_prior/alvedro_prior.py
globalbedo_prior/ga_utils.py
globalbedo_prior.egg-info/PKG-INFO
globalbedo_prior.egg-info/SOURCES.txt
globalbedo_prior.egg-info/dependency_links.txt
globalbedo_prior.egg-info/entry_points.txt
globalbedo_prior.egg-info/top_level.txt