Metadata-Version: 1.0
Name: globalbedo-prior
Version: 1.0.2
Summary: A Python implementation of the GlobAlbedo prior calculations.
Home-page: http://github.com/jgomezdans/globalbedo_prior/
Author: J Gomez-Dans
Author-email: j.gomez-dans@ucl.ac.uk
License: UNKNOWN
Platform: UNKNOWN
